{"version": "1.2.0",
 "packagesDir": ".lake/packages",
 "packages":
 [{"url": "https://github.com/leanprover-community/mathlib4",
   "type": "git",
   "subDir": null,
   "scope": "leanprover-community",
   "rev": "fabf563a7c95a166b8d7b6efca11c8b4dc9d911f",
   "name": "mathlib",
   "manifestFile": "lake-manifest.json",
   "inputRev": "v4.31.0",
   "inherited": false,
   "configFile": "lakefile.lean"},
  {"url": "https://github.com/verse-lab/Lentil.git",
   "type": "git",
   "subDir": null,
   "scope": "",
   "rev": "bc3bc567928c4a4d0158496b7c18412f10b3304f",
   "name": "Lentil",
   "manifestFile": "lake-manifest.json",
   "inputRev": "main",
   "inherited": false,
   "configFile": "lakefile.lean"},
  {"url": "https://github.com/BasisResearch/lean.py",
   "type": "git",
   "subDir": null,
   "scope": "",
   "rev": "a626fcbf61ec11d7506e57fe161f35e1b92f47da",
   "name": "LeanPy",
   "manifestFile": "lake-manifest.json",
   "inputRev": "main",
   "inherited": false,
   "configFile": "lakefile.lean"},
  {"url": "https://github.com/verse-lab/veil.git",
   "type": "git",
   "subDir": null,
   "scope": "",
   "rev": "6a12daa8d3e0e8a9808a40ecab17ca030b557063",
   "name": "veil",
   "manifestFile": "lake-manifest.json",
   "inputRev": "main",
   "inherited": false,
   "configFile": "lakefile.lean"},
  {"url": "https://github.com/leanprover-community/plausible",
   "type": "git",
   "subDir": null,
   "scope": "leanprover-community",
   "rev": "63045536fe95024e6c18fc7b48e03f506701c5bc",
   "name": "plausible",
   "manifestFile": "lake-manifest.json",
   "inputRev": "v4.31.0",
   "inherited": false,
   "configFile": "lakefile.toml"},
  {"url": "https://github.com/leanprover-community/LeanSearchClient",
   "type": "git",
   "subDir": null,
   "scope": "leanprover-community",
   "rev": "c5d5b8fe6e5158def25cd28eb94e4141ad97c843",
   "name": "LeanSearchClient",
   "manifestFile": "lake-manifest.json",
   "inputRev": "main",
   "inherited": true,
   "configFile": "lakefile.toml"},
  {"url": "https://github.com/leanprover-community/import-graph",
   "type": "git",
   "subDir": null,
   "scope": "leanprover-community",
   "rev": "5c7542ed018c78194f1e2b903eaf6a792b74c03d",
   "name": "importGraph",
   "manifestFile": "lake-manifest.json",
   "inputRev": "main",
   "inherited": true,
   "configFile": "lakefile.toml"},
  {"url": "https://github.com/leanprover-community/ProofWidgets4",
   "type": "git",
   "subDir": null,
   "scope": "leanprover-community",
   "rev": "24b0d9dc081c5423f8eec7e866c441e5184f29d9",
   "name": "proofwidgets",
   "manifestFile": "lake-manifest.json",
   "inputRev": "main",
   "inherited": true,
   "configFile": "lakefile.lean"},
  {"url": "https://github.com/leanprover-community/aesop",
   "type": "git",
   "subDir": null,
   "scope": "leanprover-community",
   "rev": "e3cb2f741431ce31bf73549fb52316a57368b06f",
   "name": "aesop",
   "manifestFile": "lake-manifest.json",
   "inputRev": "master",
   "inherited": true,
   "configFile": "lakefile.toml"},
  {"url": "https://github.com/leanprover-community/quote4",
   "type": "git",
   "subDir": null,
   "scope": "leanprover-community",
   "rev": "f46324995fca5f0483b742e4eb4daec7f4ee50d2",
   "name": "Qq",
   "manifestFile": "lake-manifest.json",
   "inputRev": "master",
   "inherited": true,
   "configFile": "lakefile.toml"},
  {"url": "https://github.com/leanprover-community/batteries",
   "type": "git",
   "subDir": null,
   "scope": "leanprover-community",
   "rev": "fa08db58b30eb033edcdab331bba000827f9f785",
   "name": "batteries",
   "manifestFile": "lake-manifest.json",
   "inputRev": "main",
   "inherited": true,
   "configFile": "lakefile.toml"},
  {"url": "https://github.com/pandaman64/lean-regex.git",
   "type": "git",
   "subDir": "regex",
   "scope": "",
   "rev": "cdfe4c8469625510e0e4d5b3d2af51e6acd8e100",
   "name": "Regex",
   "manifestFile": "lake-manifest.json",
   "inputRev": "v4.29.0",
   "inherited": true,
   "configFile": "lakefile.toml"},
  {"url": "https://github.com/leanprover/Pantograph.git",
   "type": "git",
   "subDir": null,
   "scope": "",
   "rev": "842c0fe6e76b0771cc7f7939604c7a0b90e17433",
   "name": "Pantograph",
   "manifestFile": "lake-manifest.json",
   "inputRev": "dev",
   "inherited": true,
   "configFile": "lakefile.lean"},
  {"url": "https://github.com/ufmg-smite/lean-smt.git",
   "type": "git",
   "subDir": null,
   "scope": "",
   "rev": "3c6b049eb0ccf7c331f3686e12e5f5b666bdd30a",
   "name": "smt",
   "manifestFile": "lake-manifest.json",
   "inputRev": "3c6b049eb0ccf7c331f3686e12e5f5b666bdd30a",
   "inherited": true,
   "configFile": "lakefile.lean"},
  {"url": "https://github.com/leanprover-community/lean-auto.git",
   "type": "git",
   "subDir": null,
   "scope": "",
   "rev": "36d85bf6372f1a35fb5487325d1ef965b33c6296",
   "name": "auto",
   "manifestFile": "lake-manifest.json",
   "inputRev": "36d85bf6372f1a35fb5487325d1ef965b33c6296",
   "inherited": true,
   "configFile": "lakefile.lean"},
  {"url": "https://github.com/leanprover/lean4-cli",
   "type": "git",
   "subDir": null,
   "scope": "leanprover",
   "rev": "92564e5770e4d09f2d86dfbf8ada1e9c715b384c",
   "name": "Cli",
   "manifestFile": "lake-manifest.json",
   "inputRev": "v4.31.0",
   "inherited": true,
   "configFile": "lakefile.toml"},
  {"url": "https://github.com/argumentcomputer/LSpec.git",
   "type": "git",
   "subDir": null,
   "scope": "",
   "rev": "db76512cd5266f0c576d561d8c69e2dc4890bea5",
   "name": "LSpec",
   "manifestFile": "lake-manifest.json",
   "inputRev": "db76512cd5266f0c576d561d8c69e2dc4890bea5",
   "inherited": true,
   "configFile": "lakefile.toml"},
  {"url": "https://github.com/abdoo8080/lean-cvc5.git",
   "type": "git",
   "subDir": null,
   "scope": "",
   "rev": "20a6b2f8f108d8c83b706b3502744e571303c23e",
   "name": "cvc5",
   "manifestFile": "lake-manifest.json",
   "inputRev": "20a6b2f",
   "inherited": true,
   "configFile": "lakefile.lean"}],
 "name": "blog",
 "lakeDir": ".lake",
 "fixedToolchain": false}
